mlpro_int_openml/__init__.py
mlpro_int_openml/wrappers/__init__.py
mlpro_int_openml/wrappers/streams.py
mlpro_int_openml-1.1.0.dist-info/licenses/LICENSE
mlpro_int_openml-1.1.0.dist-info/METADATA
mlpro_int_openml-1.1.0.dist-info/WHEEL
mlpro_int_openml-1.1.0.dist-info/top_level.txt
mlpro_int_openml-1.1.0.dist-info/RECORD
