Metadata-Version: 2.4
Name: mlpro-int-openml
Version: 1.1.0
Summary: MLPro: Integration OpenML
Home-page: https://mlpro-int-openml.readthedocs.io
Author: MLPro Team
Author-email: mlpro@listen.fh-swf.de
Project-URL: Bug Tracker, https://mlpro-int-openml.readthedocs.io
Classifier: Programming Language :: Python :: 3
Classifier: License :: OSI Approved :: Apache Software License
Classifier: Operating System :: OS Independent
Requires-Python: >=3.10
License-File: LICENSE
Provides-Extra: full
Requires-Dist: mlpro[full]>=2.1.0; extra == "full"
Requires-Dist: openml>=0.15.1; extra == "full"
Dynamic: license-file
